<annotation>
	<folder>img</folder>
	<filename>DSC_2187.JPG</filename>
	<path>E:\Train\img\DSC_2187.JPG</path>
	<source>
		<database>Unknown</database>
	</source>
	<size>
		<width>3936</width>
		<height>2624</height>
		<depth>3</depth>
	</size>
	<segmented>0</segmented>
	<object>
		<name>good</name>
		<pose>Unspecified</pose>
		<truncated>0</truncated>
		<difficult>0</difficult>
		<bndbox>
			<xmin>1974</xmin>
			<ymin>1031</ymin>
			<xmax>2177</xmax>
			<ymax>1208</ymax>
		</bndbox>
	</object>
	<object>
		<name>good</name>
		<pose>Unspecified</pose>
		<truncated>0</truncated>
		<difficult>0</difficult>
		<bndbox>
			<xmin>1935</xmin>
			<ymin>511</ymin>
			<xmax>2130</xmax>
			<ymax>700</ymax>
		</bndbox>
	</object>
	<object>
		<name>back</name>
		<pose>Unspecified</pose>
		<truncated>0</truncated>
		<difficult>0</difficult>
		<bndbox>
			<xmin>424</xmin>
			<ymin>1056</ymin>
			<xmax>646</xmax>
			<ymax>1281</ymax>
		</bndbox>
	</object>
	<object>
		<name>back</name>
		<pose>Unspecified</pose>
		<truncated>0</truncated>
		<difficult>0</difficult>
		<bndbox>
			<xmin>2505</xmin>
			<ymin>403</ymin>
			<xmax>2744</xmax>
			<ymax>622</ymax>
		</bndbox>
	</object>
	<object>
		<name>back</name>
		<pose>Unspecified</pose>
		<truncated>0</truncated>
		<difficult>0</difficult>
		<bndbox>
			<xmin>3235</xmin>
			<ymin>1461</ymin>
			<xmax>3463</xmax>
			<ymax>1672</ymax>
		</bndbox>
	</object>
</annotation>
