<annotation>
	<folder>img</folder>
	<filename>DSC_2321.JPG</filename>
	<path>E:\Train\img\DSC_2321.JPG</path>
	<source>
		<database>Unknown</database>
	</source>
	<size>
		<width>3936</width>
		<height>2624</height>
		<depth>3</depth>
	</size>
	<segmented>0</segmented>
	<object>
		<name>good</name>
		<pose>Unspecified</pose>
		<truncated>0</truncated>
		<difficult>0</difficult>
		<bndbox>
			<xmin>1555</xmin>
			<ymin>1503</ymin>
			<xmax>1930</xmax>
			<ymax>1842</ymax>
		</bndbox>
	</object>
	<object>
		<name>good</name>
		<pose>Unspecified</pose>
		<truncated>0</truncated>
		<difficult>0</difficult>
		<bndbox>
			<xmin>1475</xmin>
			<ymin>1986</ymin>
			<xmax>1864</xmax>
			<ymax>2314</ymax>
		</bndbox>
	</object>
	<object>
		<name>back</name>
		<pose>Unspecified</pose>
		<truncated>0</truncated>
		<difficult>0</difficult>
		<bndbox>
			<xmin>477</xmin>
			<ymin>958</ymin>
			<xmax>760</xmax>
			<ymax>1239</ymax>
		</bndbox>
	</object>
	<object>
		<name>back</name>
		<pose>Unspecified</pose>
		<truncated>0</truncated>
		<difficult>0</difficult>
		<bndbox>
			<xmin>749</xmin>
			<ymin>1564</ymin>
			<xmax>1030</xmax>
			<ymax>1822</ymax>
		</bndbox>
	</object>
	<object>
		<name>back</name>
		<pose>Unspecified</pose>
		<truncated>0</truncated>
		<difficult>0</difficult>
		<bndbox>
			<xmin>1369</xmin>
			<ymin>831</ymin>
			<xmax>1658</xmax>
			<ymax>1125</ymax>
		</bndbox>
	</object>
</annotation>
