<annotation>
	<folder>img</folder>
	<filename>DSC_2354.JPG</filename>
	<path>E:\Train\img\DSC_2354.JPG</path>
	<source>
		<database>Unknown</database>
	</source>
	<size>
		<width>3936</width>
		<height>2624</height>
		<depth>3</depth>
	</size>
	<segmented>0</segmented>
	<object>
		<name>good</name>
		<pose>Unspecified</pose>
		<truncated>0</truncated>
		<difficult>0</difficult>
		<bndbox>
			<xmin>2129</xmin>
			<ymin>1361</ymin>
			<xmax>2351</xmax>
			<ymax>1557</ymax>
		</bndbox>
	</object>
	<object>
		<name>good</name>
		<pose>Unspecified</pose>
		<truncated>0</truncated>
		<difficult>0</difficult>
		<bndbox>
			<xmin>2135</xmin>
			<ymin>438</ymin>
			<xmax>2363</xmax>
			<ymax>631</ymax>
		</bndbox>
	</object>
	<object>
		<name>tower</name>
		<pose>Unspecified</pose>
		<truncated>0</truncated>
		<difficult>0</difficult>
		<bndbox>
			<xmin>22</xmin>
			<ymin>1625</ymin>
			<xmax>436</xmax>
			<ymax>2056</ymax>
		</bndbox>
	</object>
	<object>
		<name>tower</name>
		<pose>Unspecified</pose>
		<truncated>0</truncated>
		<difficult>0</difficult>
		<bndbox>
			<xmin>213</xmin>
			<ymin>325</ymin>
			<xmax>652</xmax>
			<ymax>772</ymax>
		</bndbox>
	</object>
	<object>
		<name>tower</name>
		<pose>Unspecified</pose>
		<truncated>0</truncated>
		<difficult>0</difficult>
		<bndbox>
			<xmin>969</xmin>
			<ymin>53</ymin>
			<xmax>1388</xmax>
			<ymax>475</ymax>
		</bndbox>
	</object>
	<object>
		<name>back</name>
		<pose>Unspecified</pose>
		<truncated>0</truncated>
		<difficult>0</difficult>
		<bndbox>
			<xmin>645</xmin>
			<ymin>856</ymin>
			<xmax>1073</xmax>
			<ymax>1264</ymax>
		</bndbox>
	</object>
</annotation>
